<?xml version="1.0"?>
<ROWSET>
 <ROW>
  <APPID>CONSOLE</APPID>
  <KEY>500_error_style</KEY>
  <VALUE>DebugStyle</VALUE>
  <DESCRIPTION>Posible values: DebugStyle, UserStyle</DESCRIPTION>
  <CREATED_BY>ADMIN</CREATED_BY>
  <CREATED_DATE>2016-05-27T17:18:59</CREATED_DATE>
  <MODIFIED_BY>ADMIN</MODIFIED_BY>
  <MODIFIED_DATE>2016-05-27T17:22:20</MODIFIED_DATE>
 </ROW>
 <ROW>
  <APPID>CONSOLE</APPID>
  <KEY>base_path</KEY>
  <VALUE>/dbax/!console?p=</VALUE>
  <DESCRIPTION>The base URL path of the Application.</DESCRIPTION>
  <CREATED_BY>-1</CREATED_BY>
  <CREATED_DATE>2015-07-17T16:18:38</CREATED_DATE>
  <MODIFIED_BY>ADMIN</MODIFIED_BY>
  <MODIFIED_DATE>2016-04-26T15:48:46</MODIFIED_DATE>
 </ROW>
 <ROW>
  <APPID>CONSOLE</APPID>
  <KEY>encoding</KEY>
  <VALUE>UTF-8</VALUE>
  <DESCRIPTION>Database Encoding. Indicates the charset encoding HTTP header</DESCRIPTION>
  <CREATED_BY>-1</CREATED_BY>
  <CREATED_DATE>2015-07-17T16:18:38</CREATED_DATE>
  <MODIFIED_BY>ADMIN</MODIFIED_BY>
  <MODIFIED_DATE>2016-04-26T15:48:46</MODIFIED_DATE>
 </ROW>
 <ROW>
  <APPID>CONSOLE</APPID>
  <KEY>log_level</KEY>
  <VALUE>debug</VALUE>
  <DESCRIPTION>Log level: none,error,warn,info,debug,trace</DESCRIPTION>
  <CREATED_BY>-1</CREATED_BY>
  <CREATED_DATE>2015-07-17T16:18:38</CREATED_DATE>
  <MODIFIED_BY>ADMIN</MODIFIED_BY>
  <MODIFIED_DATE>2016-05-27T17:29:33</MODIFIED_DATE>
 </ROW>
 <ROW>
  <APPID>CONSOLE</APPID>
  <KEY>resources_url</KEY>
  <DESCRIPTION>Resources location (images, js, css etc...)</DESCRIPTION>
  <CREATED_BY>-1</CREATED_BY>
  <CREATED_DATE>2015-07-17T16:18:38</CREATED_DATE>
  <MODIFIED_BY>ADMIN</MODIFIED_BY>
  <MODIFIED_DATE>2016-05-24T14:15:47</MODIFIED_DATE>
 </ROW>
 <ROW>
  <APPID>CONSOLE</APPID>
  <KEY>session_cookie_name</KEY>
  <VALUE>DBAX_CONSOLE_SESSION</VALUE>
  <DESCRIPTION>Session cookie name.</DESCRIPTION>
  <CREATED_BY>-1</CREATED_BY>
  <CREATED_DATE>2015-07-17T16:18:38</CREATED_DATE>
  <MODIFIED_BY>ADMIN</MODIFIED_BY>
  <MODIFIED_DATE>2016-04-26T15:48:46</MODIFIED_DATE>
 </ROW>
</ROWSET>
